pyrobloxbot/__init__.py
pyrobloxbot/exceptions.py
pyrobloxbot/literals.py
pyrobloxbot-1.0.9.dist-info/METADATA
pyrobloxbot-1.0.9.dist-info/WHEEL
pyrobloxbot-1.0.9.dist-info/licenses/LICENSE
pyrobloxbot-1.0.9.dist-info/RECORD
