Metadata-Version: 2.1
Name: pyrobloxbot
Version: 1.0.9
Summary: A python library to control the roblox character and interact with game ui through keyboard inputs
Project-URL: Homepage, https://github.com/Mews/py-roblox-bot
Project-URL: Issues, https://github.com/Mews/py-roblox-bot/issues
Author-email: Mews <tiraraspas@gmail.com>
License-File: LICENSE
Keywords: bot,keyboard,roblox
Classifier: License :: OSI Approved :: GNU General Public License v3 (GPLv3)
Classifier: Operating System :: Microsoft :: Windows
Classifier: Programming Language :: Python :: 3
Requires-Python: >=3.9
Requires-Dist: keyboard
Requires-Dist: opencv-python
Requires-Dist: pillow
Requires-Dist: pyautogui
Requires-Dist: pydirectinput
Requires-Dist: pygetwindow
Requires-Dist: pynput
Requires-Dist: pyperclip
Requires-Dist: pywin32
